<?xml version="1.0" encoding="UTF-8"?>
<!DOCTYPE model PUBLIC "-//Ericsson NMS CIF CS//CS Export Filter DTD//" "export.dtd">
<!-- Generated on Thu Mar 04 12:49:00 GMT 2021 -->
<!-- Generated from configuration valid -->
<!-- Query - Base MO SubNetwork=ONRM_RootMo,SubNetwork=MGW,MeContext=MGw01,ManagedElement=MGw01; Scope 8 -->
<model>
<mo fdn="SubNetwork=ONRM_RootMo,SubNetwork=MGW,MeContext=MGw01,ManagedElement=MGw01" mimName="ONRM" mimVersion="13.2.4" lastModified="1614862140137">
 <attr name="userLabel">MGw01</attr>
 <attr name="nodeVersion">W15A</attr>
 <attr name="siteRef">SubNetwork=ONRM_RootMo,Site=MSMGw01</attr>
 <attr name="managedElementType">
  <seq count="1">
    <item>MGW</item>
  </seq>
 </attr>
 </mo>
 <!-- No filter found for MO SubNetwork=ONRM_RootMo,SubNetwork=MGW,MeContext=MGw01,ManagedElement=MGw01,MgwFunction=1 -->
</model>
<!-- Generated 1 entries -->
